{
  "class_to_idx": {
    "BACKGROUND_Google": 0,
    "Faces": 1,
    "Faces_easy": 2,
    "Leopards": 3,
    "Motorbikes": 4,
    "accordion": 5,
    "airplanes": 6,
    "anchor": 7,
    "ant": 8,
    "barrel": 9,
    "bass": 10,
    "beaver": 11,
    "binocular": 12,
    "bonsai": 13,
    "brain": 14,
    "brontosaurus": 15,
    "buddha": 16,
    "butterfly": 17,
    "camera": 18,
    "cannon": 19,
    "car_side": 20,
    "ceiling_fan": 21,
    "cellphone": 22,
    "chair": 23,
    "chandelier": 24,
    "cougar_body": 25,
    "cougar_face": 26,
    "crab": 27,
    "crayfish": 28,
    "crocodile": 29,
    "crocodile_head": 30,
    "cup": 31,
    "dalmatian": 32,
    "dollar_bill": 33,
    "dolphin": 34,
    "dragonfly": 35,
    "electric_guitar": 36,
    "elephant": 37,
    "emu": 38,
    "euphonium": 39,
    "ewer": 40,
    "ferry": 41,
    "flamingo": 42,
    "flamingo_head": 43,
    "garfield": 44,
    "gerenuk": 45,
    "gramophone": 46,
    "grand_piano": 47,
    "hawksbill": 48,
    "headphone": 49,
    "hedgehog": 50,
    "helicopter": 51,
    "ibis": 52,
    "inline_skate": 53,
    "joshua_tree": 54,
    "kangaroo": 55,
    "ketch": 56,
    "lamp": 57,
    "laptop": 58,
    "llama": 59,
    "lobster": 60,
    "lotus": 61,
    "mandolin": 62,
    "mayfly": 63,
    "menorah": 64,
    "metronome": 65,
    "minaret": 66,
    "nautilus": 67,
    "octopus": 68,
    "okapi": 69,
    "pagoda": 70,
    "panda": 71,
    "pigeon": 72,
    "pizza": 73,
    "platypus": 74,
    "pyramid": 75,
    "revolver": 76,
    "rhino": 77,
    "rooster": 78,
    "saxophone": 79,
    "schooner": 80,
    "scissors": 81,
    "scorpion": 82,
    "sea_horse": 83,
    "snoopy": 84,
    "soccer_ball": 85,
    "stapler": 86,
    "starfish": 87,
    "stegosaurus": 88,
    "stop_sign": 89,
    "strawberry": 90,
    "sunflower": 91,
    "tick": 92,
    "trilobite": 93,
    "umbrella": 94,
    "watch": 95,
    "water_lilly": 96,
    "wheelchair": 97,
    "wild_cat": 98,
    "windsor_chair": 99,
    "wrench": 100,
    "yin_yang": 101
  },
  "idx_to_class": {
    "0": "BACKGROUND_Google",
    "1": "Faces",
    "2": "Faces_easy",
    "3": "Leopards",
    "4": "Motorbikes",
    "5": "accordion",
    "6": "airplanes",
    "7": "anchor",
    "8": "ant",
    "9": "barrel",
    "10": "bass",
    "11": "beaver",
    "12": "binocular",
    "13": "bonsai",
    "14": "brain",
    "15": "brontosaurus",
    "16": "buddha",
    "17": "butterfly",
    "18": "camera",
    "19": "cannon",
    "20": "car_side",
    "21": "ceiling_fan",
    "22": "cellphone",
    "23": "chair",
    "24": "chandelier",
    "25": "cougar_body",
    "26": "cougar_face",
    "27": "crab",
    "28": "crayfish",
    "29": "crocodile",
    "30": "crocodile_head",
    "31": "cup",
    "32": "dalmatian",
    "33": "dollar_bill",
    "34": "dolphin",
    "35": "dragonfly",
    "36": "electric_guitar",
    "37": "elephant",
    "38": "emu",
    "39": "euphonium",
    "40": "ewer",
    "41": "ferry",
    "42": "flamingo",
    "43": "flamingo_head",
    "44": "garfield",
    "45": "gerenuk",
    "46": "gramophone",
    "47": "grand_piano",
    "48": "hawksbill",
    "49": "headphone",
    "50": "hedgehog",
    "51": "helicopter",
    "52": "ibis",
    "53": "inline_skate",
    "54": "joshua_tree",
    "55": "kangaroo",
    "56": "ketch",
    "57": "lamp",
    "58": "laptop",
    "59": "llama",
    "60": "lobster",
    "61": "lotus",
    "62": "mandolin",
    "63": "mayfly",
    "64": "menorah",
    "65": "metronome",
    "66": "minaret",
    "67": "nautilus",
    "68": "octopus",
    "69": "okapi",
    "70": "pagoda",
    "71": "panda",
    "72": "pigeon",
    "73": "pizza",
    "74": "platypus",
    "75": "pyramid",
    "76": "revolver",
    "77": "rhino",
    "78": "rooster",
    "79": "saxophone",
    "80": "schooner",
    "81": "scissors",
    "82": "scorpion",
    "83": "sea_horse",
    "84": "snoopy",
    "85": "soccer_ball",
    "86": "stapler",
    "87": "starfish",
    "88": "stegosaurus",
    "89": "stop_sign",
    "90": "strawberry",
    "91": "sunflower",
    "92": "tick",
    "93": "trilobite",
    "94": "umbrella",
    "95": "watch",
    "96": "water_lilly",
    "97": "wheelchair",
    "98": "wild_cat",
    "99": "windsor_chair",
    "100": "wrench",
    "101": "yin_yang"
  },
  "num_classes": 102
}